debsbom/__init__.py
debsbom/cli.py
debsbom/sbom.py
debsbom/apt/cache.py
debsbom/bomreader/__init__.py
debsbom/bomreader/bomreader.py
debsbom/bomreader/cdxbomreader.py
debsbom/bomreader/spdxbomreader.py
debsbom/bomwriter/__init__.py
debsbom/bomwriter/bomwriter.py
debsbom/commands/download.py
debsbom/commands/export.py
debsbom/commands/generate.py
debsbom/commands/input.py
debsbom/commands/merge.py
debsbom/commands/repack.py
debsbom/commands/source_merge.py
debsbom/download/__init__.py
debsbom/download/download.py
debsbom/download/dscfilter.py
debsbom/download/resolver.py
debsbom/dpkg/package.py
debsbom/export/cdx.py
debsbom/export/exporter.py
debsbom/export/graphml.py
debsbom/export/spdx.py
debsbom/generate/__init__.py
debsbom/generate/cdx.py
debsbom/generate/generate.py
debsbom/generate/spdx.py
debsbom/merge/cdx.py
debsbom/merge/merge.py
debsbom/merge/spdx.py
debsbom/repack/__init__.py
debsbom/repack/cdx.py
debsbom/repack/merger.py
debsbom/repack/packer.py
debsbom/repack/spdx.py
debsbom/resolver/__init__.py
debsbom/resolver/cdx.py
debsbom/resolver/resolver.py
debsbom/resolver/spdx.py
debsbom/snapshot/__init__.py
debsbom/snapshot/client.py
debsbom/util/__init__.py
debsbom/util/compression.py
debsbom/util/progress.py
debsbom-0.3.0.dist-info/licenses/LICENSE
debsbom-0.3.0.dist-info/METADATA
debsbom-0.3.0.dist-info/WHEEL
debsbom-0.3.0.dist-info/entry_points.txt
debsbom-0.3.0.dist-info/top_level.txt
debsbom-0.3.0.dist-info/RECORD
