Metadata-Version: 2.4
Name: debsbom
Version: 0.3.0
Summary: Generate SBOMs for Debian-based distributions.
Author-email: Christoph Steiger <christoph.steiger@siemens.com>
Maintainer-email: Christoph Steiger <christoph.steiger@siemens.com>, Felix Moessbauer <felix.moessbauer@siemens.com>
License-Expression: MIT
Project-URL: Homepage, https://github.com/siemens/debsbom
Project-URL: Repository, https://github.com/siemens/debsbom.git
Classifier: Intended Audience :: Developers
Classifier: Operating System :: POSIX :: Linux
Classifier: Programming Language :: Python :: 3
Classifier: Topic :: System :: Operating System Kernels :: Linux
Classifier: Topic :: Utilities
Requires-Python: >=3.11
License-File: LICENSE
Requires-Dist: cyclonedx-python-lib>=11.0.0
Requires-Dist: packageurl-python>=0.16.0
Requires-Dist: spdx-tools>=0.8.3
Requires-Dist: python-debian>=0.1.49
Provides-Extra: dev
Requires-Dist: pytest>=6.0; extra == "dev"
Requires-Dist: pytest-cov>=6; extra == "dev"
Requires-Dist: black; extra == "dev"
Requires-Dist: beartype>=0.20; extra == "dev"
Requires-Dist: debsbom[download]; extra == "dev"
Requires-Dist: debsbom[doc]; extra == "dev"
Provides-Extra: download
Requires-Dist: requests>=2.25.1; extra == "download"
Requires-Dist: zstandard>=0.20; extra == "download"
Provides-Extra: apt
Requires-Dist: python3-apt>=2.6.0; extra == "apt"
Provides-Extra: doc
Requires-Dist: sphinx<8,>=7; extra == "doc"
Requires-Dist: sphinx-rtd-theme>=2.0.0; extra == "doc"
Requires-Dist: sphinx-autodoc-typehints>=2.0.0; extra == "doc"
Requires-Dist: sphinx-argparse>=0.2.1; extra == "doc"
Dynamic: license-file
